ocrd_cis/__init__.py
ocrd_cis/javaprocess.py
ocrd_cis/ocrd-tool.json
ocrd_cis/aio/__init__.py
ocrd_cis/aio/aio.py
ocrd_cis/aio/cli.py
ocrd_cis/align/__init__.py
ocrd_cis/align/cli.py
ocrd_cis/data/3gs.csv.gz
ocrd_cis/data/__init__.py
ocrd_cis/data/__main__.py
ocrd_cis/data/config.json
ocrd_cis/data/model.zip
ocrd_cis/data/ocrd-cis.jar
ocrd_cis/div/__init__.py
ocrd_cis/div/auswerter.py
ocrd_cis/div/clean.py
ocrd_cis/div/cli.py
ocrd_cis/div/cutter.py
ocrd_cis/div/eval.py
ocrd_cis/div/importer.py
ocrd_cis/div/lang.py
ocrd_cis/div/stats.py
ocrd_cis/div/stopwords.json
ocrd_cis/ocropy/__init__.py
ocrd_cis/ocropy/binarize.py
ocrd_cis/ocropy/cli.py
ocrd_cis/ocropy/clip.py
ocrd_cis/ocropy/common.py
ocrd_cis/ocropy/denoise.py
ocrd_cis/ocropy/deskew.py
ocrd_cis/ocropy/dewarp.py
ocrd_cis/ocropy/ocropus_rtrain.py
ocrd_cis/ocropy/recognize.py
ocrd_cis/ocropy/resegment.py
ocrd_cis/ocropy/segment.py
ocrd_cis/ocropy/train.py
ocrd_cis/ocropy/ocrolib/__init__.py
ocrd_cis/ocropy/ocrolib/chars.py
ocrd_cis/ocropy/ocrolib/common.py
ocrd_cis/ocropy/ocrolib/default.py
ocrd_cis/ocropy/ocrolib/edist.py
ocrd_cis/ocropy/ocrolib/exceptions.py
ocrd_cis/ocropy/ocrolib/ligatures.py
ocrd_cis/ocropy/ocrolib/lineest.py
ocrd_cis/ocropy/ocrolib/lstm.py
ocrd_cis/ocropy/ocrolib/morph.py
ocrd_cis/ocropy/ocrolib/psegutils.py
ocrd_cis/ocropy/ocrolib/sl.py
ocrd_cis/ocropy/ocrolib/time_morphology.py
ocrd_cis/ocropy/ocrolib/toplevel.py
ocrd_cis/ocropy/ocrolib/utils.py
ocrd_cis/postcorrect/__init__.py
ocrd_cis/postcorrect/cli.py
ocrd_cis/wer/__init__.py
ocrd_cis/wer/cli.py
ocrd_cis-0.2.0.dist-info/LICENSE
ocrd_cis-0.2.0.dist-info/METADATA
ocrd_cis-0.2.0.dist-info/WHEEL
ocrd_cis-0.2.0.dist-info/entry_points.txt
ocrd_cis-0.2.0.dist-info/top_level.txt
ocrd_cis-0.2.0.dist-info/RECORD
