Metadata-Version: 2.1
Name: ocrd_cis
Version: 0.2.0
Summary: CIS OCR-D post-correction tools and improved Ocropy1
Author-email: Florian Fink <finkf@cis.lmu.de>, Tobias Englmeier <englmeier@cis.lmu.de>, Christoph Weber <web_chris@msn.com>, Robert Sachunsky <sachunsky@informatik.uni-leipzig.de>
License: MIT
Project-URL: Homepage, https://github.com/cisocrgroup/ocrd_cis
Project-URL: Repository, https://github.com/cisocrgroup/ocrd_cis.git
Keywords: ocr,ocr-d,ocropus-ocr,post-correction
Classifier: Development Status :: 5 - Production/Stable
Classifier: Environment :: Console
Classifier: Intended Audience :: Science/Research
Classifier: Intended Audience :: Other Audience
Classifier: License :: OSI Approved :: MIT License
Classifier: Programming Language :: Python :: 3
Classifier: Programming Language :: Python :: 3 :: Only
Classifier: Topic :: Text Processing
Requires-Python: >=3.8
License-File: LICENSE
Requires-Dist: ocrd>=3.0.2
Requires-Dist: click
Requires-Dist: scipy
Requires-Dist: numpy>=1.17.0
Requires-Dist: pillow>=7.1.2
Requires-Dist: shapely>=2.0.0
Requires-Dist: scikit-image
Requires-Dist: networkx
Requires-Dist: opencv-python-headless
Requires-Dist: rapidfuzz
Provides-Extra: debug
Requires-Dist: matplotlib>3.0.0; extra == "debug"
